test/bluesky/__init__.py
test/bluesky/formatters_test.py
test/bluesky/normalizers_test.py
twitwi/__init__.py
twitwi/anonymizers.py
twitwi/constants.py
twitwi/exceptions.py
twitwi/formatters.py
twitwi/normalizers.py
twitwi/utils.py
twitwi/bluesky/__init__.py
twitwi/bluesky/constants.py
twitwi/bluesky/formatters.py
twitwi/bluesky/normalizers.py
twitwi/bluesky/types.py
twitwi/bluesky/utils.py
twitwi-0.23.0.dist-info/licenses/LICENSE.txt
twitwi-0.23.0.dist-info/METADATA
twitwi-0.23.0.dist-info/WHEEL
twitwi-0.23.0.dist-info/top_level.txt
twitwi-0.23.0.dist-info/zip-safe
twitwi-0.23.0.dist-info/RECORD
