Metadata-Version: 2.4
Name: twitwi
Version: 0.23.0
Summary: A collection of Twitter-related helper functions for python.
Home-page: http://github.com/medialab/twitwi
Author: Béatrice Mazoyer, Guillaume Plique, Benjamin Ooghe-Tabanou
Author-email: guillaume.plique@sciencespo.fr
License: MIT
Keywords: twitter
Requires-Python: >=3.8
License-File: LICENSE.txt
Requires-Dist: pytz>=2019.3
Requires-Dist: ural>=0.31.1
Requires-Dist: python-dateutil>=2.9.0
Dynamic: author
Dynamic: author-email
Dynamic: description
Dynamic: description-content-type
Dynamic: home-page
Dynamic: keywords
Dynamic: license
Dynamic: license-file
Dynamic: requires-dist
Dynamic: requires-python
Dynamic: summary
